ai_datahive/__init__.py
ai_datahive/collectors/__init__.py
ai_datahive/collectors/arxiv_collector.py
ai_datahive/collectors/base_collector.py
ai_datahive/collectors/civitai_collector.py
ai_datahive/collectors/github_collector.py
ai_datahive/collectors/zotero_collector.py
ai_datahive/collectors/models/__init__.py
ai_datahive/collectors/models/github_project.py
ai_datahive/collectors/models/media.py
ai_datahive/collectors/models/research_paper.py
ai_datahive/collectors/utils/__init__.py
ai_datahive/collectors/utils/allowed_github_parameter.py
ai_datahive/collectors/utils/arxiv_helper.py
ai_datahive/collectors/utils/custom_exceptions.py
ai_datahive/collectors/utils/github_helper.py
ai_datahive/collectors/utils/scraping_helper.py
ai_datahive/collectors/utils/zotero_helper.py
ai_datahive/dao/__init__.py
ai_datahive/dao/base_dao.py
ai_datahive/dao/dao_factory.py
ai_datahive/dao/supabase_dao.py
ai_datahive/models/__init__.py
ai_datahive/models/base_model.py
ai_datahive/models/content_base_model.py
ai_datahive/publishers/__init__.py
ai_datahive/publishers/telegram_bot.py
ai_datahive/publishers/loader/__init__.py
ai_datahive/publishers/loader/telegram_base_loader.py
ai_datahive/publishers/loader/telegram_daily_arxiv_loader.py
ai_datahive/publishers/loader/telegram_daily_trending_github_projects_loader.py
ai_datahive/publishers/loader/telegram_top_daily_image_critique_loader.py
ai_datahive/publishers/loader/telegram_top_daily_image_loader.py
ai_datahive/publishers/models/__init__.py
ai_datahive/publishers/models/telegram_group.py
ai_datahive/publishers/models/telegram_group_topic.py
ai_datahive/publishers/models/telegram_message.py
ai_datahive/services/__init__.py
ai_datahive/services/ai_backed_translation_service.py
ai_datahive/services/ai_service_factory.py
ai_datahive/services/base_ai_vision_service.py
ai_datahive/services/base_llm_service.py
ai_datahive/services/data_service.py
ai_datahive/services/openai_service.py
ai_datahive/services/prompt_service.py
ai_datahive-0.1.6.dist-info/LICENSE
ai_datahive-0.1.6.dist-info/METADATA
ai_datahive-0.1.6.dist-info/WHEEL
ai_datahive-0.1.6.dist-info/top_level.txt
ai_datahive-0.1.6.dist-info/RECORD
