Metadata-Version: 2.1
Name: ai-datahive
Version: 0.1.6
Summary: ETL Package for crawling data, transform it with AI and store it in a datastorage.
Author: Danny Gerst
Author-email: d.gerst@bizrock.de
License-File: LICENSE
Requires-Dist: python-dotenv
Requires-Dist: pydantic
Requires-Dist: inflect
Requires-Dist: pillow
Requires-Dist: requests
Requires-Dist: bs4
Requires-Dist: lxml
Requires-Dist: apscheduler
Requires-Dist: sqlalchemy
Requires-Dist: supabase
Requires-Dist: feedparser
Requires-Dist: pyzotero
Requires-Dist: python-telegram-bot[ext]
Requires-Dist: openai
